keyring_proxy_cli/__init__.py
keyring_proxy_cli/__main__.py
keyring_proxy_cli-0.2.2.dist-info/METADATA
keyring_proxy_cli-0.2.2.dist-info/WHEEL
keyring_proxy_cli-0.2.2.dist-info/entry_points.txt
keyring_proxy_cli-0.2.2.dist-info/RECORD
